{
  "name": "BombManualGenerator",
  "version": "0.3.1",
  "authors": [
    {
      "name": "Pedro Sousa",
      "email": "pedroteosousa@gmail.com",
      "maintainer": true
    }
  ],
  "description": "A library used by KTANE modules to generate manual page data",
  "license": "MIT",
  "repository": {
    "type": "git",
    "url": "https://github.com/reinodovo/bomb-manual-generator.git"
  },
  "export": {},
  "keywords": [
    "ktane"
  ],
  "platforms": [
    "native"
  ],
  "frameworks": [
    "*"
  ]
}